src/__init__.py
src/assistant.py
src/config.py
src/error_handler.py
src/handlers.py
src/knowledge.py
src/logger.py
src/memory.py
src/tools.py
src/prompts/__init__.py
src/prompts/common_prompt.py
src/prompts/core_prompt.py
src/prompts/price_query_prompt.py
src/prompts/recent_swaps_analysis_prompt.py
src/prompts/wallet_query_prompt.py
src/remote/__init__.py
src/remote/base_server.py
src/remote/combined_server.py
src/remote/exceptions.py
src/remote/function_server.py
src/remote/gateway_server.py
src/remote/models.py
src/remote/remote_processor.py
cronos_cj_ai_agent_dev-0.1.0.dist-info/LICENSE
cronos_cj_ai_agent_dev-0.1.0.dist-info/METADATA
cronos_cj_ai_agent_dev-0.1.0.dist-info/WHEEL
cronos_cj_ai_agent_dev-0.1.0.dist-info/top_level.txt
cronos_cj_ai_agent_dev-0.1.0.dist-info/RECORD
